{"1":{"conditions":["he_knows_you = true"],"false":4,"graph_data":{"height":175,"node_name":"54991141","width":327,"x":640,"y":140},"true":2,"type":"condition"},"2":{"commands":null,"graph_data":{"height":130,"node_name":"56439173","width":135,"x":1360,"y":240},"next":6,"text":"i know you!","type":"dialog"},"4":{"commands":null,"graph_data":{"height":130,"node_name":"57315173","width":135,"x":1080,"y":880},"next":6,"text":"I kill you","type":"dialog"},"6":{"commands":null,"graph_data":{"height":130,"node_name":"57266597","width":135,"x":1420,"y":880},"next":7,"text":"whatever","type":"dialog"},"7":{"commands":null,"graph_data":{"height":360,"node_name":"57195925","width":257,"x":220,"y":260},"responses":[{"conditions":null,"next":1,"text":"What"},{"conditions":null,"next":4,"text":"sos"}],"text":"Hey you!","type":"response"},"connections":[{"from":"57195925","from_port":0,"to":"54991141","to_port":0},{"from":"54991141","from_port":0,"to":"56439173","to_port":0},{"from":"54991141","from_port":1,"to":"57315173","to_port":0},{"from":"57195925","from_port":1,"to":"57315173","to_port":0},{"from":"57315173","from_port":0,"to":"57266597","to_port":0},{"from":"56439173","from_port":0,"to":"57266597","to_port":0},{"from":"57266597","from_port":0,"to":"57195925","to_port":0}],"dialog_name":"Balageda"}